yogadl/__init__.py
yogadl/_core.py
yogadl/_keys_operator.py
yogadl/_lmdb_handler.py
yogadl/constants.py
yogadl/tensorflow.py
yogadl/dataref/__init__.py
yogadl/dataref/_local_lmdb_dataref.py
yogadl/rw_coordinator/__init__.py
yogadl/rw_coordinator/_client.py
yogadl/rw_coordinator/_server.py
yogadl/rw_coordinator/communication_protocol.py
yogadl/storage/__init__.py
yogadl/storage/_cloud_storage.py
yogadl/storage/_gcs_storage.py
yogadl/storage/_lfs_storage.py
yogadl/storage/_s3_storage.py
yogadl-0.1.4.dist-info/LICENSE
yogadl-0.1.4.dist-info/METADATA
yogadl-0.1.4.dist-info/NOTICE
yogadl-0.1.4.dist-info/WHEEL
yogadl-0.1.4.dist-info/top_level.txt
yogadl-0.1.4.dist-info/RECORD
