Metadata-Version: 2.1
Name: yogadl
Version: 0.1.4
Summary: Yoga Data Layer, a flexible data layer for machine learning
Home-page: https://www.github.com/determined-ai/yogadl/
Author: Determined AI
Author-email: hello@determined.ai
License: Apache License 2.0
Platform: UNKNOWN
Classifier: License :: OSI Approved :: Apache Software License
Requires-Python: >=3.6.0
Requires-Dist: async-generator
Requires-Dist: boto3
Requires-Dist: filelock
Requires-Dist: google-cloud-storage
Requires-Dist: lmdb
Requires-Dist: lomond
Requires-Dist: websockets (>=8.0)
Provides-Extra: tf
Requires-Dist: tensorflow ; extra == 'tf'
